{
  "date": "2026-05-02",
  "attribution": "irfanokr | https://github.com/irfanokr/currency-api | Free, no-limit currency API",
  "irr": {
    "usd": 7.988e-07,
    "aed": 2.9335e-06,
    "afn": 5.13198e-05,
    "all": 6.54847e-05,
    "amd": 0.000296043,
    "ang": 1.4298e-06,
    "aoa": 0.000736922,
    "ars": 0.0011031884,
    "aud": 1.1099e-06,
    "awg": 1.4298e-06,
    "azn": 1.3592e-06,
    "bam": 1.3325e-06,
    "bbd": 1.5976e-06,
    "bdt": 9.80677e-05,
    "bgn": 1.3325e-06,
    "bhd": 3.003e-07,
    "bif": 0.0023813328,
    "bmd": 7.988e-07,
    "bnd": 1.017e-06,
    "bob": 5.5432e-06,
    "brl": 3.9736e-06,
    "bsd": 7.988e-07,
    "btn": 7.59167e-05,
    "bwp": 1.10666e-05,
    "byn": 2.2476e-06,
    "bzd": 1.5976e-06,
    "cad": 1.0858e-06,
    "cdf": 0.0018486733,
    "chf": 6.247e-07,
    "clf": 1.83e-08,
    "clp": 0.0007251126,
    "cnh": 5.4559e-06,
    "cny": 5.4615e-06,
    "cop": 0.0028959938,
    "crc": 0.0003639374,
    "cup": 1.91707e-05,
    "cve": 7.51226e-05,
    "czk": 1.66266e-05,
    "djf": 0.0001419596,
    "dkk": 5.0842e-06,
    "dop": 4.75154e-05,
    "dzd": 0.0001060989,
    "egp": 4.26024e-05,
    "ern": 1.19817e-05,
    "etb": 0.0001248343,
    "eur": 6.813e-07,
    "fjd": 1.7594e-06,
    "fkp": 5.889e-07,
    "fok": 5.0842e-06,
    "gbp": 5.89e-07,
    "gel": 2.1478e-06,
    "ggp": 5.889e-07,
    "ghs": 8.9699e-06,
    "gip": 5.889e-07,
    "gmd": 5.924e-05,
    "gnf": 0.0070085153,
    "gtq": 6.1158e-06,
    "gyd": 0.0001671397,
    "hkd": 6.258e-06,
    "hnl": 2.12824e-05,
    "hrk": 5.1332e-06,
    "htg": 0.0001044583,
    "huf": 0.0002480714,
    "idr": 0.013857184,
    "ils": 2.3518e-06,
    "imp": 5.889e-07,
    "inr": 7.59171e-05,
    "iqd": 0.001046873,
    "irr": 1.0,
    "isk": 9.80772e-05,
    "jep": 5.889e-07,
    "jmd": 0.0001256799,
    "jod": 5.663e-07,
    "jpy": 0.0001254729,
    "kes": 0.0001031439,
    "kgs": 6.9917e-05,
    "khr": 0.0031898629,
    "kid": 1.1099e-06,
    "kmf": 0.0003351732,
    "krw": 0.0011766993,
    "kwd": 2.457e-07,
    "kyd": 6.656e-07,
    "kzt": 0.0003701915,
    "lak": 0.0175405559,
    "lbp": 0.0714906173,
    "lkr": 0.0002550651,
    "lrd": 0.0001469554,
    "lsl": 1.33169e-05,
    "lyd": 5.0691e-06,
    "mad": 7.3809e-06,
    "mdl": 1.37646e-05,
    "mga": 0.0033155561,
    "mkd": 4.21049e-05,
    "mmk": 0.0016813101,
    "mnt": 0.00286913,
    "mop": 6.4457e-06,
    "mru": 3.19472e-05,
    "mur": 3.75714e-05,
    "mvr": 1.23563e-05,
    "mwk": 0.0013928737,
    "mxn": 1.39653e-05,
    "myr": 3.1711e-06,
    "mzn": 5.08687e-05,
    "nad": 1.33169e-05,
    "ngn": 0.001099114,
    "nio": 2.94424e-05,
    "nok": 7.423e-06,
    "npr": 0.0001214668,
    "nzd": 1.3542e-06,
    "omr": 3.071e-07,
    "pab": 7.988e-07,
    "pen": 2.8048e-06,
    "pgk": 3.4754e-06,
    "php": 4.90454e-05,
    "pkr": 0.0002228669,
    "pln": 2.8953e-06,
    "pyg": 0.0049761969,
    "qar": 2.9076e-06,
    "ron": 3.5338e-06,
    "rsd": 8.00035e-05,
    "rub": 5.99307e-05,
    "rwf": 0.0011692887,
    "sar": 2.9954e-06,
    "sbd": 6.3371e-06,
    "scr": 1.10827e-05,
    "sdg": 0.000407917,
    "sek": 7.3679e-06,
    "sgd": 1.0169e-06,
    "shp": 5.889e-07,
    "sle": 1.97086e-05,
    "sll": 0.0197085947,
    "sos": 0.0004563868,
    "srd": 2.99672e-05,
    "ssp": 0.003707699,
    "stn": 1.66916e-05,
    "syp": 9.12247e-05,
    "szl": 1.33169e-05,
    "thb": 2.59516e-05,
    "tjs": 7.5087e-06,
    "tmt": 2.7956e-06,
    "tnd": 2.3047e-06,
    "top": 1.8871e-06,
    "try": 3.60544e-05,
    "ttd": 5.3931e-06,
    "tvd": 1.1099e-06,
    "twd": 2.52687e-05,
    "tzs": 0.0020870384,
    "uah": 3.51466e-05,
    "ugx": 0.0029747506,
    "uyu": 3.19086e-05,
    "uzs": 0.0095258863,
    "ves": 0.0003910454,
    "vnd": 0.0210174455,
    "vuv": 9.47511e-05,
    "wst": 2.1539e-06,
    "xaf": 0.0004468976,
    "xcd": 2.1567e-06,
    "xcg": 1.4298e-06,
    "xdr": 5.839e-07,
    "xof": 0.0004468976,
    "xpf": 8.12998e-05,
    "yer": 0.0001909501,
    "zar": 1.3303e-05,
    "zmw": 1.50619e-05,
    "zwg": 2.02425e-05,
    "zwl": 2.02425e-05
  }
}